Danas_newProject/__init__.py
Dana_s_first_project-0.1.2.dist-info/METADATA
Dana_s_first_project-0.1.2.dist-info/WHEEL
Dana_s_first_project-0.1.2.dist-info/top_level.txt
Dana_s_first_project-0.1.2.dist-info/RECORD
