Metadata-Version: 2.1
Name: Dana-s-first-project
Version: 0.1.2
Summary: Python Technology first project
Home-page: UNKNOWN
Author: Dana
Author-email: ciobanu.dana.adriana@gmail.com
License: UNKNOWN
Platform: UNKNOWN
